tkdatacanvas/__init__.py
tkdatacanvas/__main__.py
tkdatacanvas/widget.py
tkDataCanvas-0.1.1.dist-info/LICENSE
tkDataCanvas-0.1.1.dist-info/METADATA
tkDataCanvas-0.1.1.dist-info/WHEEL
tkDataCanvas-0.1.1.dist-info/top_level.txt
tkDataCanvas-0.1.1.dist-info/RECORD
