Metadata-Version: 2.1
Name: tkDataCanvas
Version: 0.1.1
Summary: Tabular data display widget for Tkinter
Home-page: https://github.com/bmjcode/tkDataCanvas
Author: Benjamin Johnson
Author-email: bmjcode@gmail.com
License: UNKNOWN
Platform: UNKNOWN
Classifier: Development Status :: 3 - Alpha
Classifier: Programming Language :: Python :: 2
Classifier: Programming Language :: Python :: 3
Classifier: License :: OSI Approved :: MIT License
Classifier: Operating System :: OS Independent
